{
    "words": [
        {"english": "band", "correct": "grup", "priority": 5, "incorrect": ["gürültülü", "mutlu"]},
        {"english": "movie", "correct": "film", "priority": 5, "incorrect": ["aptal", "zengin"]},
        {"english": "report", "correct": "rapor", "priority": 5, "incorrect": ["farklı", "güzel"]},
        {"english": "law", "correct": "hukuk", "priority": 5, "incorrect": ["soğuk", "ılık"]},
        {"english": "nature", "correct": "doğa", "priority": 5, "incorrect": ["tuz", "biber"]},
        {"english": "language", "correct": "dil", "priority": 5, "incorrect": ["fakir", "doğru"]},
        {"english": "science", "correct": "bilim", "priority": 5, "incorrect": ["balık", "et"]},
        {"english": "plant", "correct": "bitki", "priority": 5, "incorrect": ["meyve", "sebze"]},
        {"english": "character", "correct": "karakter", "priority": 5, "incorrect": ["kapalı", "hızlı"]},
        {"english": "diet", "correct": "diyet", "priority": 5, "incorrect": ["ince", "ağır"]},
        {"english": "thought", "correct": "düşünce", "priority": 5, "incorrect": ["kapalı", "hızlı"]},
        {"english": "failure", "correct": "başarısızlık", "priority": 5, "incorrect": ["alçak", "parlak"]},
        {"english": "reading", "correct": "okuma", "priority": 5, "incorrect": ["fakir", "doğru"]},
        {"english": "nutrition", "correct": "beslenme", "priority": 5, "incorrect": ["dar", "kalın"]},
        {"english": "decision", "correct": "karar", "priority": 5, "incorrect": ["masa", "kedi"]},
        {"english": "victory", "correct": "zafer", "priority": 5, "incorrect": ["zayıf", "zeki"]},
        {"english": "theory", "correct": "teori", "priority": 5, "incorrect": ["korkmuş", "heyecanlı"]},
        {"english": "camera", "correct": "kamera", "priority": 5, "incorrect": ["çirkin", "yüksek"]},
        {"english": "study", "correct": "çalışma", "priority": 5, "incorrect": ["alçak", "parlak"]},
        {"english": "technique", "correct": "teknik", "priority": 5, "incorrect": ["fakir", "doğru"]},
        {"english": "team", "correct": "takım", "priority": 5, "incorrect": ["yorgun", "hasta"]},
        {"english": "research", "correct": "araştırma", "priority": 5, "incorrect": ["çirkin", "yüksek"]},
        {"english": "defeat", "correct": "yenilgi", "priority": 5, "incorrect": ["aptal", "zengin"]},
        {"english": "important", "correct": "önemli", "priority": 5, "incorrect": ["kapı", "okul"]},
        {"english": "election", "correct": "seçim", "priority": 5, "incorrect": ["kötü", "temiz"]},
        {"english": "picture", "correct": "resim", "priority": 5, "incorrect": ["karanlık", "sessiz"]},
        {"english": "knowledge", "correct": "bilgi", "priority": 5, "incorrect": ["çiçek", "köpek"]},
        {"english": "justice", "correct": "adalet", "priority": 5, "incorrect": ["eski", "iyi"]},
        {"english": "culture", "correct": "kültür", "priority": 5, "incorrect": ["bulut", "taş"]},
        {"english": "technology", "correct": "teknoloji", "priority": 5, "incorrect": ["süt", "çay"]},
        {"english": "publishing", "correct": "yayıncılık", "priority": 5, "incorrect": ["yavaş", "erken"]},
        {"english": "relationship", "correct": "ilişki", "priority": 5, "incorrect": ["yemek", "içmek"]},
        {"english": "script", "correct": "senaryo", "priority": 5, "incorrect": ["geç", "aynı"]},
        {"english": "photography", "correct": "fotoğrafçılık", "priority": 5, "incorrect": ["alçak", "parlak"]},
        {"english": "method", "correct": "yöntem", "priority": 5, "incorrect": ["zayıf", "zeki"]},
        {"english": "match", "correct": "maç", "priority": 5, "incorrect": ["kapalı", "hızlı"]},
        {"english": "gallery", "correct": "galeri", "priority": 5, "incorrect": ["üzgün", "kızgın"]},
        {"english": "literature", "correct": "edebiyat", "priority": 5, "incorrect": ["yorgun", "hasta"]},
        {"english": "society", "correct": "toplum", "priority": 5, "incorrect": ["elma", "yıldız"]},
        {"english": "crime", "correct": "suç", "priority": 5, "incorrect": ["serin", "yeni"]},
        {"english": "exercise", "correct": "egzersiz", "priority": 5, "incorrect": ["kısa", "geniş"]},
        {"english": "album", "correct": "albüm", "priority": 5, "incorrect": ["üzgün", "kızgın"]},
        {"english": "author", "correct": "yazar", "priority": 5, "incorrect": ["aptal", "zengin"]},
        {"english": "talent", "correct": "yetenek", "priority": 5, "incorrect": ["gürültülü", "mutlu"]},
        {"english": "competition", "correct": "yarışma", "priority": 5, "incorrect": ["sağlıklı", "güçlü"]},
        {"english": "creativity", "correct": "yaratıcılık", "priority": 5, "incorrect": ["geç", "aynı"]},
        {"english": "solution", "correct": "çözüm", "priority": 5, "incorrect": ["kapalı", "hızlı"]},
        {"english": "environment", "correct": "çevre", "priority": 5, "incorrect": ["gözlük", "balık"]},
        {"english": "director", "correct": "yönetmen", "priority": 5, "incorrect": ["farklı", "güzel"]},
        {"english": "plot", "correct": "kurgu", "priority": 5, "incorrect": ["yavaş", "erken"]},
        {"english": "opportunity", "correct": "fırsat", "priority": 5, "incorrect": ["araba", "ev"]},
        {"english": "principle", "correct": "ilke", "priority": 5, "incorrect": ["yorgun", "hasta"]},
        {"english": "novel", "correct": "roman", "priority": 5, "incorrect": ["zayıf", "zeki"]},
        {"english": "goal", "correct": "hedef", "priority": 5, "incorrect": ["farklı", "güzel"]},
        {"english": "coach", "correct": "antrenör", "priority": 5, "incorrect": ["fakir", "doğru"]},
        {"english": "skill", "correct": "beceri", "priority": 5, "incorrect": ["karanlık", "sessiz"]},
        {"english": "hobby", "correct": "hobi", "priority": 5, "incorrect": ["üzgün", "kızgın"]},
        {"english": "media", "correct": "medya", "priority": 5, "incorrect": ["kirli", "kolay"]},
        {"english": "medicine", "correct": "tıp", "priority": 5, "incorrect": ["küçük", "uzun"]},
        {"english": "theater", "correct": "tiyatro", "priority": 5, "incorrect": ["fakir", "doğru"]},
        {"english": "player", "correct": "oyuncu", "priority": 5, "incorrect": ["yanlış", "açık"]},
        {"english": "security", "correct": "güvenlik", "priority": 5, "incorrect": ["hafif", "sıcak"]},
        {"english": "practice", "correct": "pratik", "priority": 5, "incorrect": ["sağlıklı", "güçlü"]},
        {"english": "health", "correct": "sağlık", "priority": 5, "incorrect": ["susuz", "büyük"]},
        {"english": "economy", "correct": "ekonomi", "priority": 5, "incorrect": ["ayakkabı", "elbise"]},
        {"english": "actress", "correct": "aktris", "priority": 5, "incorrect": ["zayıf", "zeki"]},
        {"english": "history", "correct": "tarih", "priority": 5, "incorrect": ["güneş", "kuş"]},
        {"english": "news", "correct": "haber", "priority": 5, "incorrect": ["zor", "boş"]},
        {"english": "education", "correct": "eğitim", "priority": 5, "incorrect": ["kahve", "peynir"]},
        {"english": "music", "correct": "müzik", "priority": 5, "incorrect": ["çirkin", "yüksek"]},
        {"english": "success", "correct": "başarı", "priority": 5, "incorrect": ["çirkin", "yüksek"]},
        {"english": "challenge", "correct": "meydan okuma", "priority": 5, "incorrect": ["geç", "yanlış"]},
        {"english": "skill", "correct": "beceri", "priority": 5, "incorrect": ["aptal", "zengin"]},
        {"english": "poem", "correct": "şiir", "priority": 5, "incorrect": ["sağlıklı", "güçlü"]},
        {"english": "journalism", "correct": "gazetecilik", "priority": 5, "incorrect": ["geç", "aynı"]},
        {"english": "stadium", "correct": "stadyum", "priority": 5, "incorrect": ["geç", "aynı"]},
        {"english": "experience", "correct": "deneyim", "priority": 5, "incorrect": ["kitap", "su"]},
        {"english": "writing", "correct": "yazma", "priority": 5, "incorrect": ["yanlış", "açık"]},
        {"english": "actor", "correct": "aktör", "priority": 5, "incorrect": ["sağlıklı", "güçlü"]},
        {"english": "expression", "correct": "ifade", "priority": 5, "incorrect": ["yanlış", "açık"]},
        {"english": "editing", "correct": "düzenleme", "priority": 5, "incorrect": ["kapalı", "hızlı"]},
        {"english": "sculpture", "correct": "heykel", "priority": 5, "incorrect": ["korkmuş", "heyecanlı"]},
        {"english": "approach", "correct": "yaklaşım", "priority": 5, "incorrect": ["yanlış", "açık"]},
        {"english": "painting", "correct": "tablo", "priority": 5, "incorrect": ["gürültülü", "mutlu"]},
        {"english": "problem", "correct": "sorun", "priority": 5, "incorrect": ["yavaş", "erken"]},
        {"english": "experiment", "correct": "deney", "priority": 5, "incorrect": ["karanlık", "sessiz"]},
        {"english": "freedom", "correct": "özgürlük", "priority": 5, "incorrect": ["pişirmek", "aç"]},
        {"english": "university", "correct": "üniversite", "priority": 5, "incorrect": ["ekmek", "şeker"]},
        {"english": "concert", "correct": "konser", "priority": 5, "incorrect": ["farklı", "güzel"]},
        {"english": "communication", "correct": "iletişim", "priority": 5, "incorrect": ["dolu", "zengin"]},
        {"english": "evidence", "correct": "kanıt", "priority": 5, "incorrect": ["üzgün", "kızgın"]},
        {"english": "performance", "correct": "performans", "priority": 5, "incorrect": ["korkmuş", "heyecanlı"]},
        {"english": "game", "correct": "oyun", "priority": 5, "incorrect": ["korkmuş", "heyecanlı"]},
        {"english": "scene", "correct": "sahne", "priority": 5, "incorrect": ["yanlış", "açık"]},
        {"english": "art", "correct": "sanat", "priority": 5, "incorrect": ["şapka", "ay"]},
        {"english": "imagination", "correct": "hayal", "priority": 5, "incorrect": ["yavaş", "erken"]},
        {"english": "song", "correct": "şarkı", "priority": 5, "incorrect": ["karanlık", "sessiz"]},
        {"english": "population", "correct": "nüfus", "priority": 5, "incorrect": ["sandalye", "pencere"]},
        {"english": "government", "correct": "hükümet", "priority": 5, "incorrect": ["portakal", "muz"]},
        {"english": "discovery", "correct": "keşif", "priority": 5, "incorrect": ["gürültülü", "mutlu"]}
    ]
}
